{
    "HorizonLayout": [{
            "layout": "logo",
            "showMenu": false,
            "showSearch": false,
            "showLogo": true,
            "showCart": false,
            "showNotification": false,
            "menuIcon": {
                "name": "text_justifyleft",
                "fontFamily": "CupertinoIcons"
            },
            "pos": 100,
            "image": "https://i.imgur.com/iYB6PCN.png",
            "isBulk": true
        },
        {
            "isSafeArea": false,
            "showSearch": true,
            "usePrimaryColor": true,
            "borderInput": true,
            "title": "Articles, Video, Audio and More,.....",
            "backgroundColor": "ffffffff",
            "alignment": "centerLeft",
            "fontWeight": 0,
            "radius": 9.0,
            "fontSize": 16.0,
            "textOpacity": 0.5,
            "marginLeft": 20.0,
            "marginRight": 20.0,
            "marginBottom": 0.0,
            "marginTop": 10.0,
            "paddingLeft": 5.0,
            "paddingRight": 15.0,
            "paddingTop": 0.0,
            "paddingBottom": 0.0,
            "height": 45.0,
            "boxShadow": {
                "blurRadius": 79.7979797979798,
                "colorOpacity": 0.04,
                "spreadRadius": 0.0,
                "x": 0.0,
                "y": 10.0
            },
            "rotate": [],
            "minWidth": 0.0,
            "layout": "header_search",
            "isBulk": false,
            "pos": 200
        },
        {
            "layout": "category",
            "type": "text",
            "wrap": false,
            "showShortDescription": true,
            "size": 1.2,
            "radius": 19.0,
            "spacing": 12.0,
            "items": [{
                    "colors": ["#333333"],
                    "originalColor": true,
                    "keepDefaultTitle": true,
                    "showDescription": false,
                    "title": "Discover"
                },
                {
                    "colors": ["#333333"],
                    "originalColor": true,
                    "keepDefaultTitle": true,
                    "showDescription": false,
                    "title": "News"
                },
                {
                    "colors": ["#333333"],
                    "originalColor": true,
                    "keepDefaultTitle": true,
                    "showDescription": false,
                    "title": "Most Viewed"
                },
                {
                    "colors": ["#333333"],
                    "originalColor": true,
                    "keepDefaultTitle": true,
                    "showDescription": false,
                    "title": "Saved"
                }
            ],
            "line": false,
            "marginLeft": 18.0,
            "marginRight": 0.0,
            "marginTop": 25.0,
            "marginBottom": 15.0,
            "pos": 300,
            "paddingX": 10.0,
            "paddingY": 22.0,
            "marginX": 0.0,
            "marginY": 0.0,
            "hideTitle": false,
            "noBackground": true,
            "imageBorderStyle": "solid",
            "imageSpacing": 0.0,
            "labelFontSize": 16.0,
            "boxShadow": {
                "blurRadius": 12.121212121212121,
                "x": 0.0,
                "y": 0.0,
                "colorOpacity": 0.03
            },
            "isBulk": false
        },
        {
            "layout": "bannerImage",
            "design": "swiper",
            "fit": "cover",
            "items": [{
                    "image": "https://i.imgur.com/nFgLP7x.png",
                    "showSubcategory": false,
                    "bannerWithProduct": false,
                    "defaultShowProduct": false,
                    "products": []
                },
                {
                    "image": "https://i.imgur.com/e2j6abB.png",
                    "showSubcategory": false,
                    "bannerWithProduct": false,
                    "defaultShowProduct": false,
                    "products": []
                }
            ],
            "marginBottom": 5.0,
            "height": 0.2,
            "marginTop": 5.0,
            "radius": 13.7,
            "padding": 0.0,
            "title": {
                "isSafeArea": false,
                "showSearch": false,
                "usePrimaryColor": true,
                "borderInput": false,
                "title": "Hot Topics",
                "type": "static",
                "alignment": "centerLeft",
                "fontWeight": 700,
                "fontSize": 22.0,
                "textOpacity": 1.0,
                "marginLeft": 20.0,
                "marginRight": 0.0,
                "marginBottom": 16.0,
                "marginTop": 5.0,
                "paddingLeft": 5.0,
                "paddingRight": 15.0,
                "paddingTop": 0.0,
                "paddingBottom": 0.0,
                "height": 30.9,
                "rotate": [],
                "minWidth": 0.0
            },
            "enableParallax": false,
            "parallaxImageRatio": 1.2,
            "isHorizontal": false,
            "isSlider": true,
            "autoPlay": false,
            "intervalTime": 3,
            "showNumber": false,
            "isBlur": false,
            "showBackground": false,
            "upHeight": 0.0,
            "parallax": false,
            "pos": 400
        },
        {
            "layout": "bannerImage",
            "design": "static",
            "fit": "cover",
            "marginLeft": 20.0,
            "items": [{
                "padding": 0.0,
                "image": "https://i.imgur.com/KYLUW7v.png",
                "button": {
                    "text": "View Detail",
                    "backgroundColor": "#7f56d9",
                    "textColor": "#FFFFFF",
                    "x": 0.1,
                    "y": 0.9
                },
                "title": {
                    "text": "Connect with doctors &\nget suggestions",
                    "fontFamily": "Roboto",
                    "fontSize": 20.0,
                    "color": "#000000",
                    "x": 0.9,
                    "y": -0.6,
                    "enableShadow": false
                },
                "description": {
                    "text": "Connect now and get\nexpert insights",
                    "fontFamily": "Roboto",
                    "fontSize": 14.0,
                    "color": "#000000",
                    "x": 0.2,
                    "y": 0.1,
                    "enableShadow": false
                },
                "radius": 20.0,
                "showSubcategory": false,
                "bannerWithProduct": false,
                "defaultShowProduct": false,
                "products": []
            }],
            "marginBottom": 0.0,
            "height": 0.3,
            "marginRight": 20.0,
            "marginTop": 10.0,
            "title": {
                "isSafeArea": false,
                "showSearch": false,
                "usePrimaryColor": true,
                "borderInput": false,
                "title": "Get Tips",
                "type": "static",
                "alignment": "centerLeft",
                "fontWeight": 700,
                "fontSize": 22.0,
                "textOpacity": 1.0,
                "marginLeft": 0.0,
                "marginRight": 0.0,
                "marginBottom": 16.0,
                "marginTop": 5.0,
                "paddingLeft": 5.0,
                "paddingRight": 15.0,
                "paddingTop": 0.0,
                "paddingBottom": 0.0,
                "height": 30.9,
                "rotate": [],
                "minWidth": 0.0
            },
            "enableParallax": false,
            "parallaxImageRatio": 1.2,
            "isHorizontal": false,
            "parallax": false,
            "pos": 500
        },
        {
            "layout": "largeCard",
            "isSnapping": false,
            "rows": 1,
            "columns": 0,
            "imageBoxfit": "cover",
            "imageRatio": 1.2,
            "hMargin": 6.0,
            "vMargin": 0.0,
            "hPadding": 10.0,
            "vPadding": 0.0,
            "pos": 600,
            "showStockStatus": true,
            "enableRating": true,
            "hideTitle": false,
            "hideStore": false,
            "hidePrice": false,
            "featured": false,
            "showHeart": false,
            "showCartButton": false,
            "cartIconRadius": 9.0,
            "showQuantity": false,
            "showCartIconColor": false,
            "showCartIcon": true,
            "enableBottomAddToCart": false,
            "cardDesign": "card",
            "borderRadius": 3.0,
            "name": "❤️ Cycle Phases and Period",
            "image": "",
            "backgroundRadius": 10.0,
            "showCountDown": false,
            "onSale": false,
            "hideEmptyProductListRating": false,
            "showOnlyImage": false,
            "showCartButtonWithQuantity": false,
            "parallax": false,
            "parallaxImageRatio": 1.2,
            "hideEmptyProductLayout": false,
            "productListItemHeight": 125.0,
            "isBulk": true,
            "isPreviewing": null
        },
        {
            "name": "Women Fashion",
            "layout": "staggered",
            "isSnapping": true,
            "pos": 700,
            "isBulk": true,
            "image": "",
            "borderRadius": 3.0,
            "hMargin": 6.0,
            "vMargin": 0.0,
            "hPadding": 6.0,
            "vPadding": 2.0,
            "marginBGP": {
                "left": 0.0,
                "right": 0.0,
                "top": 0.0,
                "bottom": 0.0
            },
            "cardDesign": "card",
            "backgroundRadius": 10.0,
            "showCountDown": false,
            "onSale": false,
            "rows": 1,
            "columns": 3,
            "imageRatio": 1.2,
            "imageBoxfit": "cover",
            "hidePrice": false,
            "hideStore": false,
            "hideTitle": false,
            "enableRating": true,
            "showStockStatus": true,
            "hideEmptyProductListRating": false,
            "showHeart": false,
            "showCartButton": false,
            "showCartIcon": true,
            "showCartIconColor": false,
            "cartIconRadius": 9.0,
            "showQuantity": false,
            "enableBottomAddToCart": true,
            "showOnlyImage": false,
            "showCartButtonWithQuantity": false,
            "parallax": false,
            "parallaxImageRatio": 1.2,
            "hideEmptyProductLayout": false,
            "productListItemHeight": 125.0,
            "isPreviewing": null
        }
    ],
    "Setting": {
        "TabBarConfig": {
            "enable": true,
            "showMinimize": false,
            "isSafeArea": true,
            "color": null,
            "colorCart": "ff7f56d9",
            "colorIcon": "ff7a7b7f",
            "colorActiveIcon": "ff7f56d9",
            "iconSize": 22.968195913186673,
            "indicatorStyle": "none",
            "showFloatingClip": false,
            "showFloating": false,
            "enableOnTop": false,
            "enableDivider": true,
            "radiusTopLeft": 0.0,
            "radiusTopRight": 0.0,
            "radiusBottomLeft": 0.0,
            "radiusBottomRight": 0.0,
            "paddingLeft": 0.0,
            "paddingRight": 0.0,
            "paddingBottom": 0.0,
            "paddingTop": 0.0,
            "marginTop": 0.0,
            "marginBottom": 0.0,
            "marginLeft": 0.0,
            "marginRight": 0.0,
            "TabBarIndicator": {
                "height": null,
                "tabPosition": "bottom",
                "topRightRadius": null,
                "topLeftRadius": null,
                "bottomRightRadius": null,
                "bottomLeftRadius": null,
                "color": null,
                "horizontalPadding": null,
                "verticalPadding": null,
                "strokeWidth": null,
                "radius": null,
                "distanceFromCenter": null,
                "paintingStyle": "fill"
            },
            "TabBarFloating": {
                "position": 2,
                "radius": null,
                "color": "ffff672d",
                "location": "centerDocked",
                "width": null,
                "height": null,
                "elevation": null,
                "floatingType": "rectangle"
            }
        },
        "FontFamily": "Roboto",
        "FontHeader": "Raleway",
        "MainColor": "ff7f56d9",
        "ShowChat": true,
        "ProductListLayout": "list",
        "StickyHeader": false,
        "ProductDetail": "fullSizeImageType"
    },
    "TabBar": [{
            "layout": "page",
            "icon": "calendar_today_outlined",
            "fontFamily": "MaterialIcons",
            "label": "Today",
            "pos": 100,
            "visible": true,
            "defaultTab": false,
            "fullscreen": false,
            "url": "https://inspireui.com",
            "title": "InspireUI"
        },
        {
            "layout": "list-blog",
            "icon": "rectangle_grid_1x2",
            "fontFamily": "CupertinoIcons",
            "pos": 200,
            "defaultTab": false,
            "fullscreen": false,
            "visible": false
        },
        {
            "layout": "home",
            "icon": "square_grid_2x2_fill",
            "fontFamily": "CupertinoIcons",
            "label": "Insights",
            "pos": 300,
            "defaultTab": true,
            "fullscreen": false
        },
        {
            "layout": "cart",
            "pos": 400,
            "fontFamily": "CupertinoIcons",
            "icon": "bag",
            "categoryLayout": "cart",
            "defaultTab": false,
            "fullscreen": false,
            "visible": false
        },
        {
            "layout": "page",
            "icon": "chat_bubble_outline",
            "fontFamily": "MaterialIcons",
            "label": "Chat",
            "pos": 500,
            "defaultTab": false,
            "fullscreen": false,
            "url": "https://inspireui.com",
            "title": "InspireUI"
        },
        {
            "fontFamily": "CupertinoIcons",
            "icon": "person",
            "layout": "profile",
            "pos": 600,
            "visible": false,
            "defaultTab": false
        }
    ],
    "AppBar": {},
    "Drawer": {
        "logo": "assets/images/logo.png",
        "items": [{
                "show": true,
                "type": "home"
            },
            {
                "show": true,
                "type": "blog"
            },
            {
                "show": true,
                "type": "login"
            },
            {
                "show": true,
                "type": "category"
            }
        ]
    }

    { id: 11625, key: _marketo_deal_date, value: },
    { id: 11626, key: _marketo_deal_title, value: },
    { id: 15311, key: pageview, value: 2 },
    { id: 16925, key: _wcfm_product_views, value: 677 },
    { id: 69568, key: slide_template, value: },
    {
        id: 128312,
        key: _mstore_video_url,
        value: https: //wclovers.mstore.io/wp-content/uploads/2018/05/orange.mp4}, {id: 128313, key: _mstore_video_title, value: Silicon Orange Juice}, {id: 128314, key: _mstore_video_description, value: Silicon Orange Juice - a refreshing and healthy drink made from 100% natural ingredients. It contains no added sugar or artificial preservatives, making it a guilt-free beverage option. Enjoy the delicious taste of freshly squeezed oranges with the added benefits of silicon, which promotes healthy bones and joints.}, {id: 128315, key: _wc_min_max_quantities_min_qty, value: 0}, {id: 128316, key: _wc_min_max_quantities_max_qty, value: 0}, {id: 128317, key: _wc_min_max_quantities_step, value: 0}, {id: 128318, key: _wc_min_max_quantities_excluded, value: no}
    }
